zoomzoom/__init__.py
zoomzoom/__main__.py
zoomzoom/config_manager.py
zoomzoom/core.py
zoomzoom/gpt4o.py
zoomzoom/meeting_navigator.py
zoomzoom/readme.txt
zoomzoom/config/default_config.ini
zoomzoom-0.1.3.dist-info/METADATA
zoomzoom-0.1.3.dist-info/WHEEL
zoomzoom-0.1.3.dist-info/entry_points.txt
zoomzoom-0.1.3.dist-info/licenses/LICENSE
zoomzoom-0.1.3.dist-info/RECORD
