Metadata-Version: 2.4
Name: zoomzoom
Version: 0.1.3
Summary: An intelligent meeting assistant that enhances Zoom meetings with AI-powered analysis
Project-URL: Homepage, https://github.com/JimEverest/ZoomZoom
Project-URL: Bug Tracker, https://github.com/JimEverest/ZoomZoom/issues
Author-email: JimEverest <your.email@example.com>
License: MIT License
License-File: LICENSE
Classifier: Development Status :: 3 - Alpha
Classifier: Intended Audience :: End Users/Desktop
Classifier: License :: OSI Approved :: MIT License
Classifier: Operating System :: Microsoft :: Windows
Classifier: Programming Language :: Python :: 3
Classifier: Topic :: Office/Business :: Scheduling
Requires-Python: >=3.6
Requires-Dist: configparser>=5.0.0
Requires-Dist: openai>=1.0.0
Requires-Dist: requests>=2.0.0
Requires-Dist: uiautomation>=2.0.0
